[
  {
    "id": 1,
    "image": "",
    "name": "Inner Peace Abstract",
    "clicked": false
  },
  {
    "id": 2,
    "image": "",
    "name": "Lord Ganesha Green Theme",
    "clicked": false
  },
  {
    "id": 3,
    "image": "",
    "name": "Lord Krishna",
    "clicked": false
  },
  {
    "id": 4,
    "image": "",
    "name": "Desert Journey",
    "clicked": false
  },
  {
    "id": 5,
    "image": "",
    "name": "Mystical Clouds",
    "clicked": false
  },
  {
    "id": 6,
    "image": "",
    "name": "Night City Skyline",
    "clicked": false
  },
  {
    "id": 7,
    "image": "",
    "name": "Sitar Maiden",
    "clicked": false
  },
  {
    "id": 8,
    "image": "",
    "name": "Yoga",
    "clicked": false
  },
  {
    "id": 9,
    "image": "",
    "name": "Lord Jesus",
    "clicked": false
  },
  {
    "id": 10,
    "image": "",
    "name": "Mystical Spiral",
    "clicked": false
  },
  {
    "id": 11,
    "image": "",
    "name": "Lord Ganesha Orange Theme",
    "clicked": false
  },
  {
    "id": 12,
    "image": "",
    "name": "Lord Ganesha In Nature",
    "clicked": false
  }
]